addrpy/__init__.py
addrpy/addrPatterns.py
addrpy/patternFactory.py
addrpy/patternStore.py
addrpy-0.1.dist-info/LICENSE.txt
addrpy-0.1.dist-info/METADATA
addrpy-0.1.dist-info/WHEEL
addrpy-0.1.dist-info/top_level.txt
addrpy-0.1.dist-info/RECORD
