Metadata-Version: 2.1
Name: addrpy
Version: 0.1
Summary: Address Parsing Library
Home-page: UNKNOWN
Author: Gaurav Gurjar
Author-email: ggurjar333@gmail.com
License: UNKNOWN
Platform: UNKNOWN
License-File: LICENSE.txt
